aioping/__init__.py
aioping-0.4.0.dist-info/LICENSE.txt
aioping-0.4.0.dist-info/METADATA
aioping-0.4.0.dist-info/WHEEL
aioping-0.4.0.dist-info/top_level.txt
aioping-0.4.0.dist-info/RECORD
